fastlowess/__init__.py
fastlowess/__version__.py
fastlowess/_core.abi3.so
fastlowess/_core.pyi
fastlowess/py.typed
fastlowess-0.99.10.dist-info/METADATA
fastlowess-0.99.10.dist-info/WHEEL
fastlowess-0.99.10.dist-info/licenses/LICENSE-APACHE
fastlowess-0.99.10.dist-info/licenses/LICENSE-MIT
fastlowess-0.99.10.dist-info/RECORD
