Metadata-Version: 2.4
Name: fastlowess
Version: 0.99.10
Classifier: Development Status :: 5 - Production/Stable
Classifier: Intended Audience :: Science/Research
Classifier: License :: OSI Approved :: MIT License
Classifier: License :: OSI Approved :: Apache Software License
Classifier: Programming Language :: Rust
Classifier: Programming Language :: Python :: 3
Classifier: Programming Language :: Python :: 3.8
Classifier: Programming Language :: Python :: 3.9
Classifier: Programming Language :: Python :: 3.10
Classifier: Programming Language :: Python :: 3.11
Classifier: Programming Language :: Python :: 3.12
Classifier: Programming Language :: Python :: 3.13
Classifier: Programming Language :: Python :: 3.14
Classifier: Programming Language :: Python :: Implementation :: CPython
Classifier: Topic :: Scientific/Engineering :: Mathematics
Classifier: Topic :: Scientific/Engineering :: Information Analysis
Classifier: Operating System :: OS Independent
Requires-Dist: numpy>=1.20.0
License-File: LICENSE-MIT
License-File: LICENSE-APACHE
Summary: High-performance LOWESS smoothing for Python.
Keywords: lowess,smoothing,statistics,regression,numpy
Home-Page: https://github.com/thisisamirv/lowess-project
Author-email: Amir Valizadeh <thisisamirv@gmail.com>
License-Expression: MIT OR Apache-2.0
Requires-Python: >=3.8
Project-URL: Changelog, https://github.com/thisisamirv/lowess-project/CHANGELOG.md
Project-URL: Documentation, https://lowess.readthedocs.io/
Project-URL: Repository, https://github.com/thisisamirv/lowess-project
